AUTHORS
LICENSE
MANIFEST.in
TODO
ez_setup.py
setup.py
GraphGit.egg-info/PKG-INFO
GraphGit.egg-info/SOURCES.txt
GraphGit.egg-info/dependency_links.txt
GraphGit.egg-info/requires.txt
GraphGit.egg-info/top_level.txt
bin/graphgit
graphgit/__init__.py
graphgit/constants.py
graphgit/constants.pyc
graphgit/core.py