Metadata-Version: 1.0
Name: GraphGit
Version: 0.1.1
Summary: Git repository graph generator
Home-page: https://github.com/codemaniac/graphgit
Author: Ashish Prasad (codemaniac)
Author-email: ashish.ap.rao@gmail.com
License: BSD
Keywords: git repository graph visualization network analytics
Platform: UNKNOWN
